zebra_day/__init__.py
zebra_day/cmd_mgr.py
zebra_day/exceptions.py
zebra_day/logging_config.py
zebra_day/paths.py
zebra_day/print_mgr.py
zebra_day/zpl_renderer.py
zebra_day/bin/__init__.py
zebra_day/bin/fetch_zebra_config.py
zebra_day/bin/generate_coord_grid_zpl.py
zebra_day/bin/print_zpl_from_file.py
zebra_day/bin/probe_new_label_dimensions.py
zebra_day/bin/scan_for_networed_zebra_printers.py
zebra_day/bin/scan_for_networed_zebra_printers_arp_scan.sh
zebra_day/bin/scan_for_networed_zebra_printers_curl.sh
zebra_day/bin/zserve.py
zebra_day/cli/__init__.py
zebra_day/cli/cognito.py
zebra_day/cli/gui.py
zebra_day/cli/printer.py
zebra_day/cli/template.py
zebra_day/etc/Monoid-Regular-HalfTight-Dollar-0-1-l.ttf
zebra_day/etc/printer_config.json
zebra_day/etc/printer_config.template.json
zebra_day/etc/tmp_printers0.json
zebra_day/etc/tmp_printers374.json
zebra_day/etc/tmp_printers383.json
zebra_day/etc/tmp_printers450.json
zebra_day/etc/tmp_printers504.json
zebra_day/etc/tmp_printers608.json
zebra_day/etc/tmp_printers657.json
zebra_day/etc/tmp_printers838.json
zebra_day/etc/tmp_printers839.json
zebra_day/etc/tmp_printers933.json
zebra_day/etc/tmp_printers957.json
zebra_day/etc/label_styles/blank.zpl
zebra_day/etc/label_styles/cornersStripOf4Squares_1inX1in.zpl
zebra_day/etc/label_styles/corners_1inX2in.zpl
zebra_day/etc/label_styles/corners_20cmX30cm.zpl
zebra_day/etc/label_styles/corners_smallTube.zpl
zebra_day/etc/label_styles/corners_unspecifiedDimensions.zpl
zebra_day/etc/label_styles/generic_2inX1in.zpl
zebra_day/etc/label_styles/plate_1inX0.25in.zpl
zebra_day/etc/label_styles/plate_1inX0.25inHD.zpl
zebra_day/etc/label_styles/smallTubeWdotHD_prod.zpl
zebra_day/etc/label_styles/smallTubeWdot_corners.zpl
zebra_day/etc/label_styles/smallTubeWdot_prod.zpl
zebra_day/etc/label_styles/smallTubeWdot_prodAlt1.zpl
zebra_day/etc/label_styles/smallTubeWdot_prodAlt1b.zpl
zebra_day/etc/label_styles/smallTubeWdot_prodV2.zpl
zebra_day/etc/label_styles/smallTubeWdot_reagent.zpl
zebra_day-1.0.2.dist-info/licenses/LICENSE
zebra_day-1.0.2.dist-info/METADATA
zebra_day-1.0.2.dist-info/WHEEL
zebra_day-1.0.2.dist-info/entry_points.txt
zebra_day-1.0.2.dist-info/top_level.txt
zebra_day-1.0.2.dist-info/RECORD
