Metadata-Version: 2.4
Name: zebra_day
Version: 1.0.2
Summary: A Python library to manage a Zebra printer fleet and an API for ZPL print requests.
Home-page: https://github.com/Daylily-Informatics/zebra_day
Author: John Major
Author-email: John Major <john@daylilyinformatics.com>
License: MIT
Project-URL: Homepage, https://github.com/Daylily-Informatics/zebra_day
Project-URL: Repository, https://github.com/Daylily-Informatics/zebra_day.git
Project-URL: Issues, https://github.com/Daylily-Informatics/zebra_day/issues
Keywords: zebra,printer,zpl,label,barcode,fleet
Classifier: Development Status :: 4 - Beta
Classifier: Intended Audience :: Developers
Classifier: Intended Audience :: Manufacturing
Classifier: License :: OSI Approved :: MIT License
Classifier: Operating System :: OS Independent
Classifier: Programming Language :: Python :: 3
Classifier: Programming Language :: Python :: 3.10
Classifier: Programming Language :: Python :: 3.11
Classifier: Programming Language :: Python :: 3.12
Classifier: Programming Language :: Python :: 3.13
Classifier: Topic :: Printing
Classifier: Topic :: System :: Hardware
Requires-Python: >=3.10
License-File: LICENSE
Requires-Dist: yaml-config-day>=0.0.5
Requires-Dist: requests>=2.28.0
Requires-Dist: pytz>=2023.3
Requires-Dist: fastapi>=0.109.0
Requires-Dist: uvicorn[standard]>=0.27.0
Requires-Dist: jinja2>=3.1.0
Requires-Dist: pydantic>=2.0.0
Requires-Dist: python-multipart>=0.0.6
Requires-Dist: typer>=0.9.0
Requires-Dist: rich>=13.0.0
Requires-Dist: pillow>=10.0.0
Requires-Dist: zint-bindings>=1.2.0
Provides-Extra: dev
Requires-Dist: pytest>=7.4.0; extra == "dev"
Requires-Dist: pytest-cov>=4.0.0; extra == "dev"
Requires-Dist: ipython>=8.16.0; extra == "dev"
Provides-Extra: lint
Requires-Dist: black>=23.0.0; extra == "lint"
Requires-Dist: ruff>=0.1.0; extra == "lint"
Requires-Dist: mypy>=1.0.0; extra == "lint"
Provides-Extra: docs
Requires-Dist: mkdocs>=1.5.0; extra == "docs"
Requires-Dist: mkdocs-material>=9.0.0; extra == "docs"
Provides-Extra: auth
Requires-Dist: daylily-cognito>=0.1.10; extra == "auth"
Requires-Dist: python-jose[cryptography]>=3.3.0; extra == "auth"
Requires-Dist: boto3>=1.26.0; extra == "auth"
Provides-Extra: all
Requires-Dist: zebra_day[auth,dev,docs,lint]; extra == "all"
Dynamic: author
Dynamic: home-page
Dynamic: license-file
